rankedpairs/__init__.py
rankedpairs/election.py
rankedpairs/rp.py
rankedpairs/utils.py
rankedpairs-1.0.0.dist-info/LICENSE
rankedpairs-1.0.0.dist-info/METADATA
rankedpairs-1.0.0.dist-info/WHEEL
rankedpairs-1.0.0.dist-info/top_level.txt
rankedpairs-1.0.0.dist-info/RECORD
